README.md
setup.py
mlnd_EPC_distributions/Binomialdistribution.py
mlnd_EPC_distributions/Gaussiandistribution.py
mlnd_EPC_distributions/Generaldistribution.py
mlnd_EPC_distributions/__init__.py
mlnd_EPC_distributions.egg-info/PKG-INFO
mlnd_EPC_distributions.egg-info/SOURCES.txt
mlnd_EPC_distributions.egg-info/dependency_links.txt
mlnd_EPC_distributions.egg-info/not-zip-safe
mlnd_EPC_distributions.egg-info/top_level.txt