Metadata-Version: 1.0
Name: mlnd-EPC-distributions
Version: 0.2
Summary: Gaussian distributions
Home-page: UNKNOWN
Author: emile
Author-email: fake@email.com
License: UNKNOWN
Platform: UNKNOWN
